treeproject/__init__.py
treeproject/content.py
treeproject/pretty.py
treeproject/summary.py
treeproject/tree.py
treeproject-0.1.0.dist-info/METADATA
treeproject-0.1.0.dist-info/WHEEL
treeproject-0.1.0.dist-info/licenses/LICENSE
treeproject-0.1.0.dist-info/RECORD
