Metadata-Version: 2.4
Name: treeproject
Version: 0.1.0
Summary: treeproject is a lightweight Python library that scans a directory and builds a clean anytree-based representation of its filesystem structure. Files and folders become navigable nodes, enabling filtering, traversal, visualization, and content extraction.
License: MIT
License-File: LICENSE
Keywords: filesystem,tree,anytree,path,utilities
Author: Dylan Lebreton
Author-email: dylan.lebreton1996@gmail.com
Requires-Python: >=3.10,<4.0
Classifier: License :: OSI Approved :: MIT License
Classifier: Operating System :: OS Independent
Classifier: Programming Language :: Python
Classifier: Programming Language :: Python :: 3
Classifier: Programming Language :: Python :: 3.10
Classifier: Programming Language :: Python :: 3.11
Classifier: Programming Language :: Python :: 3.12
Classifier: Programming Language :: Python :: 3.13
Classifier: Programming Language :: Python :: 3.14
Classifier: Topic :: Software Development :: Libraries
Classifier: Topic :: Utilities
Requires-Dist: anytree (>=2.13.0,<3.0.0)
Requires-Dist: pathspec (>=0.12.1,<0.13.0)
Project-URL: Documentation, https://github.com/dylan-lebreton/treeproject#readme
Project-URL: Homepage, https://github.com/dylan-lebreton/treeproject
Project-URL: Repository, https://github.com/dylan-lebreton/treeproject
